contacts2csv/__init__.py
contacts2csv/contacts2csv.py
contacts2csv-0.0.6.dist-info/LICENSE.txt
contacts2csv-0.0.6.dist-info/METADATA
contacts2csv-0.0.6.dist-info/WHEEL
contacts2csv-0.0.6.dist-info/top_level.txt
contacts2csv-0.0.6.dist-info/RECORD
